README.md
setup.py
ksifteq/Deriva_KRX.py
ksifteq/__init__.py
ksifteq/eFriend.py
ksifteq.egg-info/PKG-INFO
ksifteq.egg-info/SOURCES.txt
ksifteq.egg-info/dependency_links.txt
ksifteq.egg-info/requires.txt
ksifteq.egg-info/top_level.txt