Metadata-Version: 1.2
Name: ksifteq
Version: 0.0.2
Summary: KSIF API
Home-page: https://github.com/ksifteq/ksifteq
Author: KSIF Tech
Author-email: meenmo@outlook.com
License: UNKNOWN
Keywords: ksif,eFriend,KRX,derivatives
Platform: UNKNOWN
Classifier: Programming Language :: Python :: 3
Classifier: License :: OSI Approved :: MIT License
Classifier: Operating System :: OS Independent
Requires-Python: >=3.5
